common_util_py/cli/__init__.py
common_util_py/cli/test_timeout.py
common_util_py/cli/timeout.py
common_util_py/datetime/__init__.py
common_util_py/db/__init__.py
common_util_py/db/mysql.py
common_util_py/db/sql.py
common_util_py/files/__init__.py
common_util_py/files/json_file.py
common_util_py/files/test_files.py
common_util_py/files/test_json_file.py
common_util_py/httpclient/__init__.py
common_util_py/httpclient/test_httpclient.py
common_util_py/httpclient/get/sample.py
common_util_py/ip/__init__.py
common_util_py/ip/hostname.py
common_util_py/ip/ipv4.py
common_util_py/ip/ipv6.py
common_util_py/logger/__init__.py
common_util_py/logger/log.py
common_util_py/mailer/__init__.py
common_util_py/mailer/email.py
common_util_py/mailer/gmail.py
common_util_py/mailer/mailer.py
common_util_py/mailer/test_email_address.py
common_util_py/maths/__init__.py
common_util_py/matrixclient/__init__.py
common_util_py/matrixclient/htmlmsg.py
common_util_py/matrixclient/matrixclient.py
common_util_py-0.0.28.dist-info/licenses/LICENSE
common_util_py-0.0.28.dist-info/METADATA
common_util_py-0.0.28.dist-info/WHEEL
common_util_py-0.0.28.dist-info/top_level.txt
common_util_py-0.0.28.dist-info/RECORD
