Metadata-Version: 2.4
Name: common_util_py
Version: 0.0.28
Summary: Common Python utility modules
Home-page: https://github.com/jasonwee/common-util-py
Author: Jason Wee
Author-email: Jason Wee <jason@weetech.ch>, Jason Wee <peichieh@gmail.com>
Maintainer-email: Jason Wee <jason@weetech.ch>, Jason Wee <peichieh@gmail.com>
License-Expression: Apache-2.0
Project-URL: Homepage, https://www.weetech.ch
Project-URL: Documentation, https://github.com/jasonwee/common-util-py
Project-URL: Source, https://github.com/jasonwee/common-util-py
Project-URL: Tracker, https://github.com/jasonwee/common-util-py/issues
Keywords: utilities,common,python,sql,weetech
Classifier: Operating System :: POSIX :: Linux
Classifier: Topic :: Software Development :: Libraries :: Python Modules
Classifier: Programming Language :: Python :: 3
Requires-Python: >=3.8
License-File: LICENSE
Requires-Dist: PyMySQL>=1.1.1
Requires-Dist: matrix-nio>=0.20.0
Requires-Dist: SQLAlchemy>=2.0.41
Requires-Dist: mysql-connector-python>=9.4.0
Provides-Extra: dev
Requires-Dist: pytest>=8.4.1; extra == "dev"
Requires-Dist: twine>=6.1.0; extra == "dev"
Requires-Dist: ruff>=0.12.7; extra == "dev"
Requires-Dist: mypy>=1.17.1; extra == "dev"
Requires-Dist: build>=1.3.0; extra == "dev"
Dynamic: author
Dynamic: home-page
Dynamic: license-file
